dagster_deltalake_polars/__init__.py
dagster_deltalake_polars/deltalake_polars_type_handler.py
dagster_deltalake_polars/py.typed
dagster_deltalake_polars/version.py
dagster_deltalake_polars-0.28.13.dist-info/licenses/LICENSE
dagster_deltalake_polars-0.28.13.dist-info/METADATA
dagster_deltalake_polars-0.28.13.dist-info/WHEEL
dagster_deltalake_polars-0.28.13.dist-info/top_level.txt
dagster_deltalake_polars-0.28.13.dist-info/RECORD
